lenzf/__init__.py
lenzf/lenzf.py
lenzf-0.1.dist-info/METADATA
lenzf-0.1.dist-info/WHEEL
lenzf-0.1.dist-info/top_level.txt
lenzf-0.1.dist-info/RECORD
