Metadata-Version: 2.1
Name: lenzf
Version: 0.1
Summary: A custom Python module to calculate the length of various data types
Author: Yashwant Gokul P
Author-email: connectwithyg@gmail.com
License: MIT
Classifier: Programming Language :: Python :: 3
Classifier: License :: OSI Approved :: MIT License
Classifier: Operating System :: OS Independent
Requires-Python: >=3.6
